pytmg/TMG.py
pytmg/TMGNetworkDevice.py
pytmg/TMGResult.py
pytmg/TMGTransceiver.py
pytmg/__init__.py
pytmg-0.0.1.dist-info/LICENSE.md
pytmg-0.0.1.dist-info/METADATA
pytmg-0.0.1.dist-info/WHEEL
pytmg-0.0.1.dist-info/top_level.txt
pytmg-0.0.1.dist-info/RECORD
