Metadata-Version: 2.1
Name: pytmg
Version: 0.0.1
Summary: A Python API client library for Cisco's Transceiver Module Group (TMG) Compatibility Matrix
Home-page: https://github.com/ChristopherJHart/pytmg
Author: Christopher Hart
Author-email: christopherjhart95@gmail.com
License: UNKNOWN
Platform: UNKNOWN
Classifier: Intended Audience :: Developers
Classifier: Programming Language :: Python :: 3
Classifier: Operating System :: OS Independent
Requires-Python: >=3.6
Requires-Dist: requests (<3.0,>=2.22.0)
